binary_database_files/__init__.py
binary_database_files/apps.py
binary_database_files/manager.py
binary_database_files/models.py
binary_database_files/settings.py
binary_database_files/storage.py
binary_database_files/urls.py
binary_database_files/utils.py
binary_database_files/views.py
binary_database_files/management/__init__.py
binary_database_files/management/commands/__init__.py
binary_database_files/management/commands/database_files_cleanup.py
binary_database_files/management/commands/database_files_dump.py
binary_database_files/management/commands/database_files_load.py
binary_database_files/management/commands/database_files_rehash.py
binary_database_files/migrations/0001_initial.py
binary_database_files/migrations/__init__.py
binary_database_files/tests/__init__.py
binary_database_files/tests/models.py
binary_database_files/tests/settings.py
binary_database_files/tests/tests.py
sicksid_django_binary_database_files-1.1.0.dist-info/DESCRIPTION.rst
sicksid_django_binary_database_files-1.1.0.dist-info/METADATA
sicksid_django_binary_database_files-1.1.0.dist-info/RECORD
sicksid_django_binary_database_files-1.1.0.dist-info/WHEEL
sicksid_django_binary_database_files-1.1.0.dist-info/metadata.json
sicksid_django_binary_database_files-1.1.0.dist-info/top_level.txt
