Metadata-Version: 2.0
Name: sicksid-django-binary-database-files
Version: 1.1.0
Summary: ('A storage system for Django that stores uploaded files in both the database and file system.', 'Sorry, copied this for now to make compatible with django 4.1 and pdm (pdm is a python package manager).', 'and python 3.11, currently i cant install without this')
Home-page: https://github.com/sicksid/django-binary-database-files/
Author: Roger Hunwicks
Author-email: roger@tonic-solutions.com
Classifier: Development Status :: 6 - Mature
Classifier: Framework :: Django
Classifier: Intended Audience :: Developers
Classifier: License :: OSI Approved :: BSD License
Classifier: Operating System :: OS Independent
Classifier: Programming Language :: Python
Classifier: Programming Language :: Python :: 3.6
Classifier: Programming Language :: Python :: 3.7
Classifier: Programming Language :: Python :: 3.8
Classifier: Programming Language :: Python :: 3.9
Classifier: Programming Language :: Python :: 3.10
Classifier: Programming Language :: Python :: 3.11
Classifier: Framework :: Django :: 2.2
Classifier: Framework :: Django :: 3.0
Classifier: Framework :: Django :: 3.1
Classifier: Framework :: Django :: 3.2
Classifier: Framework :: Django :: 4.0
Classifier: Framework :: Django :: 4.1
Requires-Python: >=3.10
License-File: LICENSE
Requires-Dist: Django (<5,>=2.2)
